LICENSE
MANIFEST.in
README.md
setup.cfg
setup.py
bitexen_client/__init__.py
bitexen_client/api.py
bitexen_client/constants.py
bitexen_client/settings.py
bitexen_client/settings_base.py
bitexen_client/version.py
bitexen_client.egg-info/PKG-INFO
bitexen_client.egg-info/SOURCES.txt
bitexen_client.egg-info/dependency_links.txt
bitexen_client.egg-info/requires.txt
bitexen_client.egg-info/top_level.txt
bitexen_client/utils/__init__.py
bitexen_client/utils/dotdict.py