Metadata-Version: 1.0
Name: bitexen-client
Version: 0.0.14
Summary: Python Client for Bitexen API
Home-page: https://github.com/Bitexen/bitexen-python
Author: Bitexen Development Team
Author-email: development@bitexen.com
License: UNKNOWN
Platform: UNKNOWN
